openauth/__init__.py
openauth/errors.py
openauth/validation.py
openauth/auth/__init__.py
openauth/auth/magic.py
openauth/auth/oauth.py
openauth/auth/social.py
openauth/models/__init__.py
openauth/models/magic.py
openauth/models/user.py
openauth-1.0.0.dist-info/LICENSE
openauth-1.0.0.dist-info/METADATA
openauth-1.0.0.dist-info/WHEEL
openauth-1.0.0.dist-info/top_level.txt
openauth-1.0.0.dist-info/RECORD
